{
  "G_0_0": "2",
  "G_0_1": "(mu**4 + 2)/(2*mu**4)",
  "G_0_2": "(mu**4 - 2*mu**3 + 3*mu**2 - 2*mu + 3)/(2*mu**4 - 4*mu**3 + 6*mu**2 - 4*mu + 2)",
  "G_0_3": "0",
  "G_0_4": "0",
  "G_0_5": "0",
  "G_0_6": "(8*mu**6 - 8*mu + 8)/mu**6",
  "G_0_7": "(-8*mu**10 + 8*mu**5 + 8*mu**4 - 16)/mu**10",
  "G_0_8": "0",
  "G_0_9": "0",
  "G_0_10": "0",
  "G_0_11": "(8*mu**6 - 24*mu**5 + 48*mu**4 - 56*mu**3 + 48*mu**2 - 16*mu)/(mu**6 - 3*mu**5 + 6*mu**4 - 7*mu**3 + 6*mu**2 - 3*mu + 1)",
  "G_0_12": "0",
  "G_0_13": "(-8*mu**10 + 40*mu**9 - 120*mu**8 + 240*mu**7 - 360*mu**6 + 400*mu**5 - 320*mu**4 + 168*mu**3 - 32*mu**2 - 16*mu)/(mu**10 - 5*mu**9 + 15*mu**8 - 30*mu**7 + 45*mu**6 - 51*mu**5 + 45*mu**4 - 30*mu**3 + 15*mu**2 - 5*mu + 1)",
  "G_0_14": "0",
  "G_0_15": "(-40*mu**5 + 96*mu**4 - 112*mu**3 + 96*mu**2 - 48*mu + 16)/(mu**16 - 3*mu**15 + 6*mu**14 - 7*mu**13 + 6*mu**12 - 3*mu**11 + mu**10)",
  "G_0_16": "(-40*mu**4 + 64*mu**3 - 56*mu**2 + 32*mu - 8)/(mu**15 - 5*mu**14 + 15*mu**13 - 30*mu**12 + 45*mu**11 - 51*mu**10 + 45*mu**9 - 30*mu**8 + 15*mu**7 - 5*mu**6 + mu**5)",
  "G_1_1": "(mu**8 + 1)/mu**8",
  "G_1_2": "(mu**8 - 2*mu**7 + 3*mu**6 - 2*mu**5 + mu**4 + 2)/(2*mu**8 - 4*mu**7 + 6*mu**6 - 4*mu**5 + 2*mu**4)",
  "G_1_3": "0",
  "G_1_4": "0",
  "G_1_5": "0",
  "G_1_6": "(-8*mu**9 + 16*mu**5 + 8*mu**3 - 8)/mu**9",
  "G_1_7": "(-8*mu**14 + 8*mu**8 + 8*mu**5 - 16)/mu**14",
  "G_1_8": "0",
  "G_1_9": "0",
  "G_1_10": "0",
  "G_1_11": "(16*mu**5 - 48*mu**4 + 96*mu**3 - 112*mu**2 + 96*mu - 40)/(mu**9 - 3*mu**8 + 6*mu**7 - 7*mu**6 + 6*mu**5 - 3*mu**4 + mu**3)",
  "G_1_12": "0",
  "G_1_13": "(-8*mu**4 + 32*mu**3 - 56*mu**2 + 64*mu - 40)/(mu**13 - 5*mu**12 + 15*mu**11 - 30*mu**10 + 45*mu**9 - 51*mu**8 + 45*mu**7 - 30*mu**6 + 15*mu**5 - 5*mu**4 + mu**3)",
  "G_1_14": "0",
  "G_1_15": "(24*mu**13 - 48*mu**12 + 56*mu**11 - 48*mu**10 + 24*mu**9 - 8*mu**8 - 40*mu**5 + 96*mu**4 - 112*mu**3 + 96*mu**2 - 48*mu + 16)/(mu**20 - 3*mu**19 + 6*mu**18 - 7*mu**17 + 6*mu**16 - 3*mu**15 + mu**14)",
  "G_1_16": "(24*mu**12 - 96*mu**11 + 224*mu**10 - 352*mu**9 + 408*mu**8 - 360*mu**7 + 240*mu**6 - 120*mu**5 + 56*mu**3 - 56*mu**2 + 32*mu - 8)/(mu**19 - 5*mu**18 + 15*mu**17 - 30*mu**16 + 45*mu**15 - 51*mu**14 + 45*mu**13 - 30*mu**12 + 15*mu**11 - 5*mu**10 + mu**9)",
  "G_2_2": "(mu**8 - 4*mu**7 + 10*mu**6 - 16*mu**5 + 19*mu**4 - 16*mu**3 + 10*mu**2 - 4*mu + 2)/(mu**8 - 4*mu**7 + 10*mu**6 - 16*mu**5 + 19*mu**4 - 16*mu**3 + 10*mu**2 - 4*mu + 1)",
  "G_2_3": "0",
  "G_2_4": "0",
  "G_2_5": "0",
  "G_2_6": "(16*mu**5 - 8)/(mu**9 - 2*mu**8 + 3*mu**7 - 2*mu**6 + mu**5)",
  "G_2_7": "(8*mu**5 - 16)/(mu**14 - 2*mu**13 + 3*mu**12 - 2*mu**11 + mu**10)",
  "G_2_8": "0",
  "G_2_9": "0",
  "G_2_10": "0",
  "G_2_11": "(-8*mu**10 + 40*mu**9 - 120*mu**8 + 240*mu**7 - 344*mu**6 + 360*mu**5 - 256*mu**4 + 112*mu**3 - 16*mu)/(mu**10 - 5*mu**9 + 15*mu**8 - 30*mu**7 + 45*mu**6 - 51*mu**5 + 45*mu**4 - 30*mu**3 + 15*mu**2 - 5*mu + 1)",
  "G_2_12": "0",
  "G_2_13": "(-8*mu**14 + 56*mu**13 - 224*mu**12 + 616*mu**11 - 1288*mu**10 + 2128*mu**9 - 2848*mu**8 + 3112*mu**7 - 2776*mu**6 + 1992*mu**5 - 1104*mu**4 + 432*mu**3 - 80*mu**2 - 16*mu)/(mu**14 - 7*mu**13 + 28*mu**12 - 77*mu**11 + 161*mu**10 - 266*mu**9 + 357*mu**8 - 393*mu**7 + 357*mu**6 - 266*mu**5 + 161*mu**4 - 77*mu**3 + 28*mu**2 - 7*mu + 1)",
  "G_2_14": "0",
  "G_2_15": "(24*mu**13 - 96*mu**12 + 224*mu**11 - 352*mu**10 + 408*mu**9 - 360*mu**8 + 240*mu**7 - 120*mu**6 + 88*mu**4 - 112*mu**3 + 96*mu**2 - 48*mu + 16)/(mu**20 - 5*mu**19 + 15*mu**18 - 30*mu**17 + 45*mu**16 - 51*mu**15 + 45*mu**14 - 30*mu**13 + 15*mu**12 - 5*mu**11 + mu**10)",
  "G_2_16": "(24*mu**13 - 144*mu**12 + 488*mu**11 - 1136*mu**10 + 2000*mu**9 - 2776*mu**8 + 3112*mu**7 - 2848*mu**6 + 2088*mu**5 - 1224*mu**4 + 560*mu**3 - 192*mu**2 + 48*mu - 8)/(mu**20 - 7*mu**19 + 28*mu**18 - 77*mu**17 + 161*mu**16 - 266*mu**15 + 357*mu**14 - 393*mu**13 + 357*mu**12 - 266*mu**11 + 161*mu**10 - 77*mu**9 + 28*mu**8 - 7*mu**7 + mu**6)",
  "G_3_3": "(16*mu**10 - 16*mu**5 + 16)/mu**10",
  "G_3_4": "0",
  "G_3_5": "0",
  "G_3_6": "0",
  "G_3_7": "0",
  "G_3_8": "0",
  "G_3_9": "(-320*mu**10 + 960*mu**9 - 1920*mu**8 + 2240*mu**7 - 1920*mu**6 + 960*mu**5 - 480*mu**4 + 960*mu**3 - 1120*mu**2 + 960*mu - 448)/(mu**10 - 3*mu**9 + 6*mu**8 - 7*mu**7 + 6*mu**6 - 3*mu**5 + mu**4)",
  "G_3_10": "(-448*mu**10 + 960*mu**9 - 1120*mu**8 + 960*mu**7 - 480*mu**6 + 960*mu**5 - 1920*mu**4 + 2240*mu**3 - 1920*mu**2 + 960*mu - 320)/(mu**22 - 3*mu**21 + 6*mu**20 - 7*mu**19 + 6*mu**18 - 3*mu**17 + mu**16)",
  "G_3_11": "0",
  "G_3_12": "0",
  "G_3_13": "0",
  "G_3_14": "0",
  "G_3_15": "0",
  "G_3_16": "0",
  "G_4_4": "(16*mu**10 - 80*mu**9 + 240*mu**8 - 480*mu**7 + 720*mu**6 - 800*mu**5 + 656*mu**4 - 368*mu**3 + 112*mu**2)/(mu**10 - 5*mu**9 + 15*mu**8 - 30*mu**7 + 45*mu**6 - 51*mu**5 + 45*mu**4 - 30*mu**3 + 15*mu**2 - 5*mu + 1)",
  "G_4_5": "0",
  "G_4_6": "0",
  "G_4_7": "0",
  "G_4_8": "0",
  "G_4_9": "(320*mu**10 - 960*mu**9 + 1920*mu**8 - 2240*mu**7 + 1920*mu**6 - 960*mu**5 + 480*mu**4 - 960*mu**3 + 1120*mu**2 - 960*mu + 448)/(mu**10 - 3*mu**9 + 6*mu**8 - 7*mu**7 + 6*mu**6 - 3*mu**5 + mu**4)",
  "G_4_10": "0",
  "G_4_11": "0",
  "G_4_12": "0",
  "G_4_13": "0",
  "G_4_14": "(448*mu**8 - 2432*mu**7 + 6400*mu**6 - 11008*mu**5 + 13312*mu**4 - 11008*mu**3 + 6400*mu**2 - 2432*mu + 448)/(mu**20 - 8*mu**19 + 36*mu**18 - 112*mu**17 + 266*mu**16 - 504*mu**15 + 784*mu**14 - 1016*mu**13 + 1107*mu**12 - 1016*mu**11 + 784*mu**10 - 504*mu**9 + 266*mu**8 - 112*mu**7 + 36*mu**6 - 8*mu**5 + mu**4)",
  "G_4_15": "0",
  "G_4_16": "0",
  "G_5_5": "(112*mu**8 - 368*mu**7 + 656*mu**6 - 800*mu**5 + 720*mu**4 - 480*mu**3 + 240*mu**2 - 80*mu + 16)/(mu**20 - 5*mu**19 + 15*mu**18 - 30*mu**17 + 45*mu**16 - 51*mu**15 + 45*mu**14 - 30*mu**13 + 15*mu**12 - 5*mu**11 + mu**10)",
  "G_5_6": "0",
  "G_5_7": "0",
  "G_5_8": "0",
  "G_5_9": "0",
  "G_5_10": "(-448*mu**10 + 960*mu**9 - 1120*mu**8 + 960*mu**7 - 480*mu**6 + 960*mu**5 - 1920*mu**4 + 2240*mu**3 - 1920*mu**2 + 960*mu - 320)/(mu**22 - 3*mu**21 + 6*mu**20 - 7*mu**19 + 6*mu**18 - 3*mu**17 + mu**16)",
  "G_5_11": "0",
  "G_5_12": "0",
  "G_5_13": "0",
  "G_5_14": "(-448*mu**8 + 2432*mu**7 - 6400*mu**6 + 11008*mu**5 - 13312*mu**4 + 11008*mu**3 - 6400*mu**2 + 2432*mu - 448)/(mu**20 - 8*mu**19 + 36*mu**18 - 112*mu**17 + 266*mu**16 - 504*mu**15 + 784*mu**14 - 1016*mu**13 + 1107*mu**12 - 1016*mu**11 + 784*mu**10 - 504*mu**9 + 266*mu**8 - 112*mu**7 + 36*mu**6 - 8*mu**5 + mu**4)",
  "G_5_15": "0",
  "G_5_16": "0",
  "G_6_6": "(1088*mu**12 - 256*mu**7 + 32*mu**6 + 64*mu**2 + 632)/mu**12",
  "G_6_7": "(416*mu**15 + 128*mu**10 + 32*mu**9 - 320*mu**5 + 632*mu**3 + 128)/mu**15",
  "G_6_8": "416",
  "G_6_9": "0",
  "G_6_10": "0",
  "G_6_11": "(672*mu**10 - 2016*mu**9 + 4032*mu**8 - 4704*mu**7 + 4032*mu**6 - 2016*mu**5 + 800*mu**4 - 768*mu**3 + 896*mu**2 - 768*mu + 320)/(mu**10 - 3*mu**9 + 6*mu**8 - 7*mu**7 + 6*mu**6 - 3*mu**5 + mu**4)",
  "G_6_12": "416",
  "G_6_13": "(-128*mu**9 + 512*mu**8 - 896*mu**7 + 1024*mu**6 - 640*mu**5 + 64*mu**4 - 256*mu**3 + 448*mu**2 - 512*mu + 320)/(mu**14 - 5*mu**13 + 15*mu**12 - 30*mu**11 + 45*mu**10 - 51*mu**9 + 45*mu**8 - 30*mu**7 + 15*mu**6 - 5*mu**5 + mu**4)",
  "G_6_14": "0",
  "G_6_15": "(-640*mu**10 + 1536*mu**9 - 1792*mu**8 + 1536*mu**7 - 768*mu**6 + 576*mu**5 - 768*mu**4 + 896*mu**3 - 768*mu**2 + 384*mu - 128)/(mu**21 - 3*mu**20 + 6*mu**19 - 7*mu**18 + 6*mu**17 - 3*mu**16 + mu**15)",
  "G_6_16": "(-640*mu**9 + 1024*mu**8 - 896*mu**7 + 512*mu**6 - 128*mu**5 + 320*mu**4 - 512*mu**3 + 448*mu**2 - 256*mu + 64)/(mu**20 - 5*mu**19 + 15*mu**18 - 30*mu**17 + 45*mu**16 - 51*mu**15 + 45*mu**14 - 30*mu**13 + 15*mu**12 - 5*mu**11 + mu**10)",
  "G_7_7": "(416*mu**20 + 32*mu**14 + 64*mu**10 + 1048*mu**8 - 256*mu**5 + 256)/mu**20",
  "G_7_8": "416/mu**12",
  "G_7_9": "0",
  "G_7_10": "0",
  "G_7_11": "(128*mu**10 - 384*mu**9 + 768*mu**8 - 896*mu**7 + 768*mu**6 - 576*mu**5 + 768*mu**4 - 1536*mu**3 + 1792*mu**2 - 1536*mu + 640)/(mu**15 - 3*mu**14 + 6*mu**13 - 7*mu**12 + 6*mu**11 - 3*mu**10 + mu**9)",
  "G_7_12": "0",
  "G_7_13": "(-64*mu**9 + 256*mu**8 - 448*mu**7 + 512*mu**6 - 320*mu**5 + 128*mu**4 - 512*mu**3 + 896*mu**2 - 1024*mu + 640)/(mu**19 - 5*mu**18 + 15*mu**17 - 30*mu**16 + 45*mu**15 - 51*mu**14 + 45*mu**13 - 30*mu**12 + 15*mu**11 - 5*mu**10 + mu**9)",
  "G_7_14": "0",
  "G_7_15": "(-416*mu**14 + 1248*mu**13 - 2496*mu**12 + 2912*mu**11 - 2816*mu**10 + 2016*mu**9 - 1312*mu**8 + 768*mu**7 - 384*mu**6 + 768*mu**5 - 1536*mu**4 + 1792*mu**3 - 1536*mu**2 + 768*mu - 256)/(mu**26 - 3*mu**25 + 6*mu**24 - 7*mu**23 + 6*mu**22 - 3*mu**21 + mu**20)",
  "G_7_16": "(-320*mu**9 + 512*mu**8 - 448*mu**7 + 256*mu**6 - 64*mu**5 + 640*mu**4 - 1024*mu**3 + 896*mu**2 - 512*mu + 128)/(mu**25 - 5*mu**24 + 15*mu**23 - 30*mu**22 + 45*mu**21 - 51*mu**20 + 45*mu**19 - 30*mu**18 + 15*mu**17 - 5*mu**16 + mu**15)",
  "G_8_8": "(416*mu**12 + 416)/mu**12",
  "G_8_9": "0",
  "G_8_10": "0",
  "G_8_11": "416",
  "G_8_12": "416",
  "G_8_13": "0",
  "G_8_14": "0",
  "G_8_15": "-416/mu**12",
  "G_8_16": "0",
  "G_9_9": "(12800*mu**22 - 76800*mu**21 + 268800*mu**20 - 640000*mu**19 + 1152000*mu**18 - 1612800*mu**17 + 1811200*mu**16 - 1670400*mu**15 + 1350400*mu**14 - 1088000*mu**13 + 982784*mu**12 - 951552*mu**11 + 850432*mu**10 - 665600*mu**9 + 481280*mu**8 - 360192*mu**7 + 291072*mu**6 - 232192*mu**5 + 161280*mu**4 - 89600*mu**3 + 37632*mu**2 - 10752*mu + 1792)/(mu**22 - 6*mu**21 + 21*mu**20 - 50*mu**19 + 90*mu**18 - 126*mu**17 + 141*mu**16 - 126*mu**15 + 90*mu**14 - 50*mu**13 + 21*mu**12 - 6*mu**11 + mu**10)",
  "G_9_10": "(8960*mu**10 - 46080*mu**9 + 133760*mu**8 - 264320*mu**7 + 389760*mu**6 - 443904*mu**5 + 389760*mu**4 - 264320*mu**3 + 133760*mu**2 - 46080*mu + 8960)/(mu**22 - 6*mu**21 + 21*mu**20 - 50*mu**19 + 90*mu**18 - 126*mu**17 + 141*mu**16 - 126*mu**15 + 90*mu**14 - 50*mu**13 + 21*mu**12 - 6*mu**11 + mu**10)",
  "G_9_11": "0",
  "G_9_12": "0",
  "G_9_13": "0",
  "G_9_14": "(8960*mu**10 - 30720*mu**9 + 39680*mu**8 - 30720*mu**7 + 15360*mu**6 - 5376*mu**5 + 11904*mu**4 - 17152*mu**3 + 14208*mu**2 - 7680*mu + 1792)/(mu**22 - 6*mu**21 + 21*mu**20 - 50*mu**19 + 90*mu**18 - 126*mu**17 + 141*mu**16 - 126*mu**15 + 90*mu**14 - 50*mu**13 + 21*mu**12 - 6*mu**11 + mu**10)",
  "G_9_15": "0",
  "G_9_16": "0",
  "G_10_10": "(1792*mu**22 - 10752*mu**21 + 37632*mu**20 - 89600*mu**19 + 161280*mu**18 - 232192*mu**17 + 291072*mu**16 - 360192*mu**15 + 481280*mu**14 - 665600*mu**13 + 850432*mu**12 - 951552*mu**11 + 982784*mu**10 - 1088000*mu**9 + 1350400*mu**8 - 1670400*mu**7 + 1811200*mu**6 - 1612800*mu**5 + 1152000*mu**4 - 640000*mu**3 + 268800*mu**2 - 76800*mu + 12800)/(mu**34 - 6*mu**33 + 21*mu**32 - 50*mu**31 + 90*mu**30 - 126*mu**29 + 141*mu**28 - 126*mu**27 + 90*mu**26 - 50*mu**25 + 21*mu**24 - 6*mu**23 + mu**22)",
  "G_10_11": "0",
  "G_10_12": "0",
  "G_10_13": "0",
  "G_10_14": "(1792*mu**10 - 7680*mu**9 + 14208*mu**8 - 17152*mu**7 + 11904*mu**6 - 5376*mu**5 + 15360*mu**4 - 30720*mu**3 + 39680*mu**2 - 30720*mu + 8960)/(mu**22 - 6*mu**21 + 21*mu**20 - 50*mu**19 + 90*mu**18 - 126*mu**17 + 141*mu**16 - 126*mu**15 + 90*mu**14 - 50*mu**13 + 21*mu**12 - 6*mu**11 + mu**10)",
  "G_10_15": "0",
  "G_10_16": "0",
  "G_11_11": "(1088*mu**16 - 8704*mu**15 + 39168*mu**14 - 121856*mu**13 + 289408*mu**12 - 548096*mu**11 + 851232*mu**10 - 1098304*mu**9 + 1185216*mu**8 - 1067392*mu**7 + 795936*mu**6 - 482496*mu**5 + 231480*mu**4 - 84256*mu**3 + 22048*mu**2 - 3328*mu + 416)/(mu**16 - 8*mu**15 + 36*mu**14 - 112*mu**13 + 266*mu**12 - 504*mu**11 + 784*mu**10 - 1016*mu**9 + 1107*mu**8 - 1016*mu**7 + 784*mu**6 - 504*mu**5 + 266*mu**4 - 112*mu**3 + 36*mu**2 - 8*mu + 1)",
  "G_11_12": "416",
  "G_11_13": "(416*mu**16 - 3328*mu**15 + 14976*mu**14 - 46592*mu**13 + 110656*mu**12 - 209792*mu**11 + 327072*mu**10 - 425152*mu**9 + 464352*mu**8 - 424960*mu**7 + 322848*mu**6 - 198720*mu**5 + 95352*mu**4 - 33184*mu**3 + 7072*mu**2)/(mu**16 - 8*mu**15 + 36*mu**14 - 112*mu**13 + 266*mu**12 - 504*mu**11 + 784*mu**10 - 1016*mu**9 + 1107*mu**8 - 1016*mu**7 + 784*mu**6 - 504*mu**5 + 266*mu**4 - 112*mu**3 + 36*mu**2 - 8*mu + 1)",
  "G_11_14": "0",
  "G_11_15": "(-640*mu**10 + 3456*mu**9 - 10240*mu**8 + 20608*mu**7 - 30720*mu**6 + 35136*mu**5 - 30720*mu**4 + 20608*mu**3 - 10240*mu**2 + 3456*mu - 640)/(mu**21 - 6*mu**20 + 21*mu**19 - 50*mu**18 + 90*mu**17 - 126*mu**16 + 141*mu**15 - 126*mu**14 + 90*mu**13 - 50*mu**12 + 21*mu**11 - 6*mu**10 + mu**9)",
  "G_11_16": "(-640*mu**9 + 2944*mu**8 - 7808*mu**7 + 13824*mu**6 - 18048*mu**5 + 17472*mu**4 - 12288*mu**3 + 6208*mu**2 - 2048*mu + 320)/(mu**20 - 8*mu**19 + 36*mu**18 - 112*mu**17 + 266*mu**16 - 504*mu**15 + 784*mu**14 - 1016*mu**13 + 1107*mu**12 - 1016*mu**11 + 784*mu**10 - 504*mu**9 + 266*mu**8 - 112*mu**7 + 36*mu**6 - 8*mu**5 + mu**4)",
  "G_12_12": "(416*mu**12 - 2496*mu**11 + 8736*mu**10 - 20800*mu**9 + 37440*mu**8 - 52416*mu**7 + 58656*mu**6 - 52416*mu**5 + 37440*mu**4 - 20800*mu**3 + 8736*mu**2 - 2496*mu + 832)/(mu**12 - 6*mu**11 + 21*mu**10 - 50*mu**9 + 90*mu**8 - 126*mu**7 + 141*mu**6 - 126*mu**5 + 90*mu**4 - 50*mu**3 + 21*mu**2 - 6*mu + 1)",
  "G_12_13": "416/(mu**12 - 6*mu**11 + 21*mu**10 - 50*mu**9 + 90*mu**8 - 126*mu**7 + 141*mu**6 - 126*mu**5 + 90*mu**4 - 50*mu**3 + 21*mu**2 - 6*mu + 1)",
  "G_12_14": "0",
  "G_12_15": "0",
  "G_12_16": "416/(mu**12 - 6*mu**11 + 21*mu**10 - 50*mu**9 + 90*mu**8 - 126*mu**7 + 141*mu**6 - 126*mu**5 + 90*mu**4 - 50*mu**3 + 21*mu**2 - 6*mu + 1)",
  "G_13_13": "(416*mu**20 - 4160*mu**19 + 22880*mu**18 - 87360*mu**17 + 255840*mu**16 - 604032*mu**15 + 1185632*mu**14 - 1971200*mu**13 + 2809088*mu**12 - 3452736*mu**11 + 3668320*mu**10 - 3361664*mu**9 + 2642008*mu**8 - 1762960*mu**7 + 985768*mu**6 - 453712*mu**5 + 168952*mu**4 - 49504*mu**3 + 11232*mu**2 - 1664*mu + 416)/(mu**20 - 10*mu**19 + 55*mu**18 - 210*mu**17 + 615*mu**16 - 1452*mu**15 + 2850*mu**14 - 4740*mu**13 + 6765*mu**12 - 8350*mu**11 + 8953*mu**10 - 8350*mu**9 + 6765*mu**8 - 4740*mu**7 + 2850*mu**6 - 1452*mu**5 + 615*mu**4 - 210*mu**3 + 55*mu**2 - 10*mu + 1)",
  "G_13_14": "0",
  "G_13_15": "(320*mu**9 - 2048*mu**8 + 6208*mu**7 - 12288*mu**6 + 17472*mu**5 - 18048*mu**4 + 13824*mu**3 - 7808*mu**2 + 2944*mu - 640)/(mu**25 - 8*mu**24 + 36*mu**23 - 112*mu**22 + 266*mu**21 - 504*mu**20 + 784*mu**19 - 1016*mu**18 + 1107*mu**17 - 1016*mu**16 + 784*mu**15 - 504*mu**14 + 266*mu**13 - 112*mu**12 + 36*mu**11 - 8*mu**10 + mu**9)",
  "G_13_16": "(416*mu**12 - 1664*mu**11 + 4160*mu**10 - 6656*mu**9 + 8224*mu**8 - 8448*mu**7 + 8896*mu**6 - 9856*mu**5 + 10336*mu**4 - 8192*mu**3 + 4736*mu**2 - 1792*mu + 320)/(mu**24 - 10*mu**23 + 55*mu**22 - 210*mu**21 + 615*mu**20 - 1452*mu**19 + 2850*mu**18 - 4740*mu**17 + 6765*mu**16 - 8350*mu**15 + 8953*mu**14 - 8350*mu**13 + 6765*mu**12 - 4740*mu**11 + 2850*mu**10 - 1452*mu**9 + 615*mu**8 - 210*mu**7 + 55*mu**6 - 10*mu**5 + mu**4)",
  "G_14_14": "(1792*mu**20 - 13568*mu**19 + 49920*mu**18 - 118272*mu**17 + 200448*mu**16 - 246272*mu**15 + 216320*mu**14 - 128768*mu**13 + 40192*mu**12 + 40192*mu**8 - 128768*mu**7 + 216320*mu**6 - 246272*mu**5 + 200448*mu**4 - 118272*mu**3 + 49920*mu**2 - 13568*mu + 1792)/(mu**32 - 11*mu**31 + 66*mu**30 - 275*mu**29 + 880*mu**28 - 2277*mu**27 + 4917*mu**26 - 9042*mu**25 + 14355*mu**24 - 19855*mu**23 + 24068*mu**22 - 25653*mu**21 + 24068*mu**20 - 19855*mu**19 + 14355*mu**18 - 9042*mu**17 + 4917*mu**16 - 2277*mu**15 + 880*mu**14 - 275*mu**13 + 66*mu**12 - 11*mu**11 + mu**10)",
  "G_14_15": "0",
  "G_14_16": "0",
  "G_15_15": "(416*mu**24 - 3328*mu**23 + 20448*mu**22 - 81152*mu**21 + 228352*mu**20 - 476256*mu**19 + 782464*mu**18 - 1043264*mu**17 + 1152408*mu**16 - 1063200*mu**15 + 823264*mu**14 - 539072*mu**13 + 317104*mu**12 - 209152*mu**11 + 202400*mu**10 - 241600*mu**9 + 269080*mu**8 - 253696*mu**7 + 198912*mu**6 - 128768*mu**5 + 68096*mu**4 - 28672*mu**3 + 9216*mu**2 - 2048*mu + 256)/(mu**36 - 8*mu**35 + 36*mu**34 - 112*mu**33 + 266*mu**32 - 504*mu**31 + 784*mu**30 - 1016*mu**29 + 1107*mu**28 - 1016*mu**27 + 784*mu**26 - 504*mu**25 + 266*mu**24 - 112*mu**23 + 36*mu**22 - 8*mu**21 + mu**20)",
  "G_15_16": "(5472*mu**17 - 34560*mu**16 + 117696*mu**15 - 266592*mu**14 + 456320*mu**13 - 620608*mu**12 + 691896*mu**11 - 640544*mu**10 + 497120*mu**9 - 324928*mu**8 + 180976*mu**7 - 88448*mu**6 + 40480*mu**5 - 18496*mu**4 + 8312*mu**3 - 3200*mu**2 + 896*mu - 128)/(mu**31 - 8*mu**30 + 36*mu**29 - 112*mu**28 + 266*mu**27 - 504*mu**26 + 784*mu**25 - 1016*mu**24 + 1107*mu**23 - 1016*mu**22 + 784*mu**21 - 504*mu**20 + 266*mu**19 - 112*mu**18 + 36*mu**17 - 8*mu**16 + mu**15)",
  "G_16_16": "(416*mu**20 - 1664*mu**19 + 9632*mu**18 - 52160*mu**17 + 211136*mu**16 - 623264*mu**15 + 1421344*mu**14 - 2604640*mu**13 + 3953368*mu**12 - 5065392*mu**11 + 5551432*mu**10 - 5240720*mu**9 + 4273288*mu**8 - 3003904*mu**7 + 1809104*mu**6 - 922272*mu**5 + 390600*mu**4 - 133232*mu**3 + 34824*mu**2 - 6320*mu + 632)/(mu**32 - 10*mu**31 + 55*mu**30 - 210*mu**29 + 615*mu**28 - 1452*mu**27 + 2850*mu**26 - 4740*mu**25 + 6765*mu**24 - 8350*mu**23 + 8953*mu**22 - 8350*mu**21 + 6765*mu**20 - 4740*mu**19 + 2850*mu**18 - 1452*mu**17 + 615*mu**16 - 210*mu**15 + 55*mu**14 - 10*mu**13 + mu**12)"
}